simplr/Agent.py
simplr/CLI.py
simplr/Cache.py
simplr/Config.py
simplr/System.py
simplr/__init__.py
simplr/simplr.py
simplr-0.0.20.dist-info/licenses/LICENSE.txt
simplr-0.0.20.dist-info/METADATA
simplr-0.0.20.dist-info/WHEEL
simplr-0.0.20.dist-info/entry_points.txt
simplr-0.0.20.dist-info/top_level.txt
simplr-0.0.20.dist-info/RECORD
